windscroll_physiocycledeco/__init__.py
windscroll_physiocycledeco-0.0.1.dist-info/METADATA
windscroll_physiocycledeco-0.0.1.dist-info/WHEEL
windscroll_physiocycledeco-0.0.1.dist-info/top_level.txt
windscroll_physiocycledeco-0.0.1.dist-info/RECORD
