Metadata-Version: 2.4
Name: windscroll-physiocycledeco
Version: 0.0.1
Summary: 类周期生理信号算法框架研究-占位包
Author-email: Zhuangyan Qin <sandubaikai@163.com>, windscroll <sandubaikai@163.com>
